[{"stackHeaders":{},"urlPath":"/assets/blte311fa28a8eba999","uid":"blte311fa28a8eba999","content_type":"image/png","file_size":"342279","tags":[],"filename":"quote-bg.png","url":"https://images.contentstack.io/v3/assets/bltaf93303b5349839e/blte311fa28a8eba999/611ab9335739461637defa66/quote-bg.png","ACL":{},"is_dir":false,"_version":1,"title":"quote-bg.png","publish_details":[{"environment":"blt246c09869cc1be88","locale":"en-us","time":"2021-08-16T19:15:00.978Z","version":1},{"environment":"blt731814740d6e13c2","locale":"en-us","time":"2021-08-16T19:15:00.978Z","version":1}]}]